lazy_constructs/__init__.py
lazy_constructs/py.typed
lazy_constructs/_jsii/__init__.py
lazy_constructs/_jsii/lazy-constructs@0.0.10.jsii.tgz
lazy_constructs-0.0.10.dist-info/LICENSE
lazy_constructs-0.0.10.dist-info/METADATA
lazy_constructs-0.0.10.dist-info/WHEEL
lazy_constructs-0.0.10.dist-info/top_level.txt
lazy_constructs-0.0.10.dist-info/RECORD
