Metadata-Version: 2.1
Name: lazy-constructs
Version: 0.0.10
Summary: lazy-constructs
Home-page: https://github.com/lazinessdevs/lazy-constructs.git
Author: Marcio Almeida<marcioadev@gmail.com>
License: Apache-2.0
Project-URL: Source, https://github.com/lazinessdevs/lazy-constructs.git
Platform: UNKNOWN
Classifier: Intended Audience :: Developers
Classifier: Operating System :: OS Independent
Classifier: Programming Language :: JavaScript
Classifier: Programming Language :: Python :: 3 :: Only
Classifier: Programming Language :: Python :: 3.7
Classifier: Programming Language :: Python :: 3.8
Classifier: Programming Language :: Python :: 3.9
Classifier: Programming Language :: Python :: 3.10
Classifier: Typing :: Typed
Classifier: Development Status :: 5 - Production/Stable
Classifier: License :: OSI Approved
Requires-Python: ~=3.7
License-File: LICENSE
Requires-Dist: aws-cdk-lib (<3.0.0,>=2.27.0)
Requires-Dist: constructs (<11.0.0,>=10.0.5)
Requires-Dist: jsii (<2.0.0,>=1.60.1)
Requires-Dist: publication (>=0.0.3)
